grynn_fplot/__init__.py
grynn_fplot/cli.py
grynn_fplot/core.py
grynn_fplot/drawdowns.py
grynn_fplot/filter_parser.py
grynn_fplot/filter_store.py
grynn_fplot/index.html
grynn_fplot/plot_option_interactive.py
grynn_fplot/serve.py
grynn_fplot/web_api.py
grynn_fplot-0.4.1.dist-info/METADATA
grynn_fplot-0.4.1.dist-info/WHEEL
grynn_fplot-0.4.1.dist-info/entry_points.txt
grynn_fplot-0.4.1.dist-info/RECORD
