Metadata-Version: 2.4
Name: grynn-fplot
Version: 0.4.1
Summary: CLI tool for plotting financial data and analyzing options
Project-URL: Homepage, https://github.com/Grynn/grynn_cli_fplot
Project-URL: Issues, https://github.com/Grynn/grynn_cli_fplot/issues
Project-URL: Repository, https://github.com/Grynn/grynn_cli_fplot
Author-email: Grynn <vishal.doshi@gmail.com>
License: MIT
Keywords: cli,finance,options,plotting,stocks
Classifier: Development Status :: 4 - Beta
Classifier: Environment :: Console
Classifier: Intended Audience :: Financial and Insurance Industry
Classifier: License :: OSI Approved :: MIT License
Classifier: Programming Language :: Python :: 3.12
Classifier: Programming Language :: Python :: 3.13
Classifier: Topic :: Office/Business :: Financial :: Investment
Requires-Python: >=3.12
Requires-Dist: click~=8.1.7
Requires-Dist: dateparser~=1.2.0
Requires-Dist: fastapi~=0.115.0
Requires-Dist: grynn-pylib
Requires-Dist: ipywidgets>=8.1.5
Requires-Dist: matplotlib>=3.9.2
Requires-Dist: mplcursors~=0.5.3
Requires-Dist: mplfinance>=0.12.9
Requires-Dist: pandas>=2.2.3
Requires-Dist: scikit-learn>=1.6.1
Requires-Dist: tabulate>=0.9.0
Requires-Dist: uvicorn~=0.32.0
Requires-Dist: yfinance
Provides-Extra: dev
Requires-Dist: ipykernel>=6.29.5; extra == 'dev'
Requires-Dist: ipython>=8.18.1; extra == 'dev'
Requires-Dist: mypy>=1.14.1; extra == 'dev'
Requires-Dist: pytest>=8.3.4; extra == 'dev'
Requires-Dist: ruff>=0.9.2; extra == 'dev'
